py_math_help/__init__.py
py_math_help-0.1.0.dist-info/METADATA
py_math_help-0.1.0.dist-info/WHEEL
py_math_help-0.1.0.dist-info/top_level.txt
py_math_help-0.1.0.dist-info/RECORD
