Metadata-Version: 2.1
Name: py-math-help
Version: 0.1.0
Summary: A Perfect Math Module For Beginners. 
Author: Harsh Gupta
Author-email: harshnkgupta@gmail.com
